AUTHORS.rst
CONTRIBUTING.rst
HISTORY.rst
LICENSE
MANIFEST.in
README.rst
setup.cfg
setup.py
docs/Makefile
docs/authors.rst
docs/conf.py
docs/contributing.rst
docs/history.rst
docs/index.rst
docs/installation.rst
docs/make.bat
docs/readme.rst
docs/usage.rst
json262/__init__.py
json262/encoders.py
json262.egg-info/PKG-INFO
json262.egg-info/SOURCES.txt
json262.egg-info/dependency_links.txt
json262.egg-info/not-zip-safe
json262.egg-info/top_level.txt
tests/__init__.py
tests/test_encoders.py
tests/test_json262.py