Metadata-Version: 1.0
Name: json262
Version: 0.2.0
Summary: JSON encoder fully compliant with ECMA-262 specification.
Home-page: https://github.com/audreyr/json262
Author: Audrey Roy
Author-email: audreyr@gmail.com
License: BSD
Keywords: json262
Platform: UNKNOWN
Classifier: Development Status :: 3 - Alpha
Classifier: Intended Audience :: Developers
Classifier: License :: OSI Approved :: BSD License
Classifier: Natural Language :: English
Classifier: Programming Language :: Python :: 2
Classifier: Programming Language :: Python :: 2.6
Classifier: Programming Language :: Python :: 2.7
Classifier: Programming Language :: Python :: 3
Classifier: Programming Language :: Python :: 3.3
